{
  "id": "pf2e-kingmaker-helper",
  "title": "Pf2e Kingmaker Helper",
  "description": "",
  "version": "0.2.2",
  "authors": [
    {
      "name": "Reyzor",
      "url": "https://www.patreon.com/Reyzor1991",
      "discord": "reyzor1991"
    }
  ],
  "languages": [
    {
      "lang": "en",
      "name": "English",
      "path": "lang/en.json"
    }
  ],
  "esmodules": [
    "main.js"
  ],
  "styles": [
    "main.css"
  ],
  "packFolders": [],
  "packs": [],
  "compatibility": {
    "minimum": "12.330",
    "verified": "12.331"
  },
  "socket": true,
  "url": "https://github.com/reyzor1991/pf2e-wiki/wiki/Pf2e-Kingmaker-Helper",
  "manifest": "https://www.dropbox.com/scl/fi/zh8sib2ppczrfve88doe2/module.json?rlkey=6vli4l4afzvpyuzp2xauhvxe3&st=5acxgp3d&dl=1",
  "download": "https://www.dropbox.com/scl/fi/konm4sdh6z4zw1vwacmjr/pf2e-kingmaker-helper.zip?rlkey=325nugnglqssr6qb7ccszi1vb&st=5v94nwrb&dl=1",
  "relationships": {
    "systems": [
      {
        "id": "pf2e",
        "type": "system",
        "manifest": "https://github.com/foundryvtt/pf2e/releases/latest/download/system.json",
        "compatibility": {
          "minimum": "6.2.1",
          "verified": "6.6.1"
        }
      }
    ],
    "requires": [
      {
        "id": "colorsettings",
        "type": "module",
        "manifest": "https://raw.githubusercontent.com/ardittristan/VTTColorSettings/master/module.json"
      }
    ]
  }
}
